Metadata-Version: 2.1
Name: ml-python-package-evgenii-v2
Version: 0.1.9
Summary: Training stuff
Author: Evgenii
License: MIT
License-File: LICENSE
Requires-Dist: scikit-learn ==0.24.1
Requires-Dist: pandas ==1.1.5
